BaomuJiShenduXuexiCongRumenDaoFangqiFix1/README.md
BaomuJiShenduXuexiCongRumenDaoFangqiFix1/__init__.py
BaomuJiShenduXuexiCongRumenDaoFangqiFix1/__main__.py
BaomuJiShenduXuexiCongRumenDaoFangqiFix1/file.epub
BaomuJiShenduXuexiCongRumenDaoFangqiFix1/index.html
BaomuJiShenduXuexiCongRumenDaoFangqiFix1/css/__init__.py
BaomuJiShenduXuexiCongRumenDaoFangqiFix1/css/annotations.css
BaomuJiShenduXuexiCongRumenDaoFangqiFix1/css/main.css
BaomuJiShenduXuexiCongRumenDaoFangqiFix1/css/normalize.css
BaomuJiShenduXuexiCongRumenDaoFangqiFix1/css/popup.css
BaomuJiShenduXuexiCongRumenDaoFangqiFix1/font/__init__.py
BaomuJiShenduXuexiCongRumenDaoFangqiFix1/font/fontello.eot
BaomuJiShenduXuexiCongRumenDaoFangqiFix1/font/fontello.svg
BaomuJiShenduXuexiCongRumenDaoFangqiFix1/font/fontello.ttf
BaomuJiShenduXuexiCongRumenDaoFangqiFix1/font/fontello.woff
BaomuJiShenduXuexiCongRumenDaoFangqiFix1/img/__init__.py
BaomuJiShenduXuexiCongRumenDaoFangqiFix1/img/annotator-glyph-sprite.png
BaomuJiShenduXuexiCongRumenDaoFangqiFix1/img/annotator-icon-sprite.png
BaomuJiShenduXuexiCongRumenDaoFangqiFix1/img/apple-touch-icon.png
BaomuJiShenduXuexiCongRumenDaoFangqiFix1/img/cancelfullscreen.png
BaomuJiShenduXuexiCongRumenDaoFangqiFix1/img/close.png
BaomuJiShenduXuexiCongRumenDaoFangqiFix1/img/fullscreen.png
BaomuJiShenduXuexiCongRumenDaoFangqiFix1/img/loader.gif
BaomuJiShenduXuexiCongRumenDaoFangqiFix1/img/menu-icon.png
BaomuJiShenduXuexiCongRumenDaoFangqiFix1/img/save.png
BaomuJiShenduXuexiCongRumenDaoFangqiFix1/img/saved.png
BaomuJiShenduXuexiCongRumenDaoFangqiFix1/img/settings-s.png
BaomuJiShenduXuexiCongRumenDaoFangqiFix1/img/settings.png
BaomuJiShenduXuexiCongRumenDaoFangqiFix1/img/star.png
BaomuJiShenduXuexiCongRumenDaoFangqiFix1/js/__init__.py
BaomuJiShenduXuexiCongRumenDaoFangqiFix1/js/epub.js
BaomuJiShenduXuexiCongRumenDaoFangqiFix1/js/epub.min.js
BaomuJiShenduXuexiCongRumenDaoFangqiFix1/js/epub.min.map
BaomuJiShenduXuexiCongRumenDaoFangqiFix1/js/hooks.min.js
baomu_ji_shendu_xuexi_cong_rumen_dao_fangqi_fix1-2025.3.25.1.dist-info/METADATA
baomu_ji_shendu_xuexi_cong_rumen_dao_fangqi_fix1-2025.3.25.1.dist-info/WHEEL
baomu_ji_shendu_xuexi_cong_rumen_dao_fangqi_fix1-2025.3.25.1.dist-info/entry_points.txt
baomu_ji_shendu_xuexi_cong_rumen_dao_fangqi_fix1-2025.3.25.1.dist-info/top_level.txt
baomu_ji_shendu_xuexi_cong_rumen_dao_fangqi_fix1-2025.3.25.1.dist-info/RECORD
